graphon_client/__init__.py
graphon_client/client.py
graphon_client-0.8.3.dist-info/METADATA
graphon_client-0.8.3.dist-info/WHEEL
graphon_client-0.8.3.dist-info/top_level.txt
graphon_client-0.8.3.dist-info/RECORD
