Metadata-Version: 2.4
Name: graphon-client
Version: 0.8.3
Summary: A Python client library for the Graphon API - Build knowledge graphs from your files
Author-email: Arbaaz Khan <arbaaz@graphon.ai>
Project-URL: Homepage, https://github.com/arbaazkhan2/graphon-client
Project-URL: Bug Reports, https://github.com/arbaazkhan2/graphon-client/issues
Project-URL: Source, https://github.com/arbaazkhan2/graphon-client
Classifier: Development Status :: 4 - Beta
Classifier: Intended Audience :: Developers
Classifier: License :: OSI Approved :: MIT License
Classifier: Operating System :: OS Independent
Classifier: Programming Language :: Python :: 3
Classifier: Programming Language :: Python :: 3.8
Classifier: Programming Language :: Python :: 3.9
Classifier: Programming Language :: Python :: 3.10
Classifier: Programming Language :: Python :: 3.11
Requires-Python: >=3.8
Requires-Dist: httpx>=0.28.1
